piplapis/__init__.py
piplapis/error.py
piplapis/search.py
piplapis/thumbnail.py
piplapis/data/__init__.py
piplapis/data/available_data.py
piplapis/data/containers.py
piplapis/data/fields.py
piplapis/data/utils.py
piplapis_python-5.3.1.dist-info/LICENSE
piplapis_python-5.3.1.dist-info/METADATA
piplapis_python-5.3.1.dist-info/WHEEL
piplapis_python-5.3.1.dist-info/top_level.txt
piplapis_python-5.3.1.dist-info/RECORD
