Metadata-Version: 2.1
Name: piplapis-python
Version: 5.3.1
Summary: Client library for use with the Pipl search API
Home-page: https://pipl.com/api
Author: Pipl
Author-email: support@pipl.com
License: http://www.apache.org/licenses/LICENSE-2.0
Platform: UNKNOWN
Classifier: Intended Audience :: Developers
Classifier: Operating System :: OS Independent
Classifier: Programming Language :: Python
Classifier: Programming Language :: Python :: 2
Classifier: Programming Language :: Python :: 3
License-File: LICENSE
Requires-Dist: six >=1.9
Requires-Dist: pytz
